dtu_hpc_cli/__init__.py
dtu_hpc_cli/client/__init__.py
dtu_hpc_cli/client/base.py
dtu_hpc_cli/client/local.py
dtu_hpc_cli/client/ssh.py
dtu_hpc_cli/config.py
dtu_hpc_cli/constants.py
dtu_hpc_cli/editor.py
dtu_hpc_cli/error.py
dtu_hpc_cli/get_command.py
dtu_hpc_cli/get_options.py
dtu_hpc_cli/history.py
dtu_hpc_cli/install.py
dtu_hpc_cli/jobs.py
dtu_hpc_cli/open_error.py
dtu_hpc_cli/open_output.py
dtu_hpc_cli/queues.py
dtu_hpc_cli/remove.py
dtu_hpc_cli/resubmit.py
dtu_hpc_cli/run.py
dtu_hpc_cli/start_time.py
dtu_hpc_cli/stats.py
dtu_hpc_cli/submit.py
dtu_hpc_cli/sync.py
dtu_hpc_cli/types.py
dtu_hpc_cli-1.4.1.dist-info/METADATA
dtu_hpc_cli-1.4.1.dist-info/WHEEL
dtu_hpc_cli-1.4.1.dist-info/entry_points.txt
dtu_hpc_cli-1.4.1.dist-info/RECORD
