Metadata-Version: 2.3
Name: dtu-hpc-cli
Version: 1.4.1
Summary: CLI to make it easier to work with the HPC cluster at the Technical University of Denmark (DTU).
License: MIT
Author: Christoffer Koo Øhrstrøm
Author-email: 2357447+ChrisFugl@users.noreply.github.com
Requires-Python: >=3.10,<4.0
Classifier: License :: OSI Approved :: MIT License
Classifier: Programming Language :: Python :: 3
Classifier: Programming Language :: Python :: 3.10
Classifier: Programming Language :: Python :: 3.11
Classifier: Programming Language :: Python :: 3.12
Classifier: Programming Language :: Python :: 3.13
Requires-Dist: fabric (>=3.2.2,<4.0.0)
Requires-Dist: gitpython (>=3.1.43,<4.0.0)
Requires-Dist: paramiko (>=3.4.1,<4.0.0)
Requires-Dist: typer (>=0.15.4,<0.16.0)
Requires-Dist: uuid (>=1.30,<2.0)
Project-URL: Changelog, https://github.com/ChrisFugl/DTU-HPC-CLI/CHANGELOG.md
Project-URL: Repository, https://github.com/ChrisFugl/DTU-HPC-CLI
